aetherlab/__init__.py
aetherlab/client.py
aetherlab/exceptions.py
aetherlab/models.py
aetherlab-0.3.1.dist-info/licenses/LICENSE
aetherlab-0.3.1.dist-info/METADATA
aetherlab-0.3.1.dist-info/WHEEL
aetherlab-0.3.1.dist-info/top_level.txt
aetherlab-0.3.1.dist-info/RECORD
