Metadata-Version: 2.4
Name: aetherlab
Version: 0.3.1
Summary: Official Python SDK for AetherLab's AI Guardrails and Compliance Platform
Home-page: https://github.com/AetherLabCo/aetherlab-community
Author: AetherLab
Author-email: AetherLab <support@aetherlab.ai>
License: MIT
Project-URL: Homepage, https://aetherlab.ai
Project-URL: Documentation, https://docs.aetherlab.ai
Project-URL: Repository, https://github.com/AetherLabCo/aetherlab-community
Project-URL: Issues, https://github.com/AetherLabCo/aetherlab-community/issues
Keywords: aetherlab,ai,guardrails,compliance,safety,llm,security,content-moderation,prompt-injection,ai-safety,chatbot-safety,ml-security,artificial-intelligence,machine-learning,nlp,openai,anthropic,gpt,claude,gemini,mistral,llama,ai-governance,responsible-ai,prompt-engineering,ai-monitoring
Classifier: Development Status :: 4 - Beta
Classifier: Intended Audience :: Developers
Classifier: Topic :: Software Development :: Libraries :: Python Modules
Classifier: Topic :: Scientific/Engineering :: Artificial Intelligence
Classifier: Topic :: Software Development :: Quality Assurance
Classifier: License :: OSI Approved :: MIT License
Classifier: Programming Language :: Python :: 3
Classifier: Programming Language :: Python :: 3.8
Classifier: Programming Language :: Python :: 3.9
Classifier: Programming Language :: Python :: 3.10
Classifier: Programming Language :: Python :: 3.11
Classifier: Programming Language :: Python :: 3.12
Classifier: Operating System :: OS Independent
Requires-Python: >=3.8
License-File: LICENSE
Requires-Dist: requests>=2.28.0
Requires-Dist: urllib3>=1.26.0
Provides-Extra: dev
Requires-Dist: pytest>=7.0.0; extra == "dev"
Requires-Dist: pytest-cov>=4.0.0; extra == "dev"
Requires-Dist: pytest-asyncio>=0.21.0; extra == "dev"
Requires-Dist: black>=23.0.0; extra == "dev"
Requires-Dist: flake8>=6.0.0; extra == "dev"
Requires-Dist: mypy>=1.0.0; extra == "dev"
Requires-Dist: twine>=4.0.0; extra == "dev"
Requires-Dist: wheel>=0.38.0; extra == "dev"
Dynamic: author
Dynamic: home-page
Dynamic: license-file
Dynamic: requires-python
